CHANGES.txt
LICENSE
MANIFEST.in
README.rst
setup.py
flyenv/__init__.py
flyenv/flyenv.py
flyenv.egg-info/PKG-INFO
flyenv.egg-info/SOURCES.txt
flyenv.egg-info/dependency_links.txt
flyenv.egg-info/entry_points.txt
flyenv.egg-info/requires.txt
flyenv.egg-info/top_level.txt