Metadata-Version: 1.1
Name: flyenv
Version: 0.0.1
Summary: a tool helps manage environment variable portably and safely
Home-page: https://github.com/luojiebin/flyenv
Author: luojiebin
Author-email: luo.jiebin@foxmail.com
License: MIT
Keywords: flyenv help environment variable management
Platform: UNKNOWN
Classifier: Environment :: Web Environment
Classifier: Intended Audience :: Developers
Classifier: Programming Language :: Python :: 2
Classifier: Programming Language :: Python :: 2.6
Classifier: Programming Language :: Python :: 2.7
Classifier: Programming Language :: Python :: 3
Classifier: Programming Language :: Python :: 3.2
Classifier: Programming Language :: Python :: 3.3
Classifier: Topic :: Internet :: WWW/HTTP
